emacnn/__init__.py
emacnn/__main__.py
emacnn/cli.py
emacnn/data.py
emacnn/features.py
emacnn/model.py
emacnn-0.0.1.dist-info/LICENSE
emacnn-0.0.1.dist-info/METADATA
emacnn-0.0.1.dist-info/WHEEL
emacnn-0.0.1.dist-info/entry_points.txt
emacnn-0.0.1.dist-info/top_level.txt
emacnn-0.0.1.dist-info/RECORD
