Metadata-Version: 2.1
Name: emacnn
Version: 0.0.1
Summary: A CLI for training a neural network on a specific YouTube channel's videos.
Home-page: https://gitlab.com/tedtramonte/emacnn
Author: Ted Tramonte
License: MIT
Project-URL: Issue tracker, https://gitlab.com/tedtramonte/emacnn/issues
Platform: UNKNOWN
Classifier: Development Status :: 3 - Alpha
Classifier: License :: OSI Approved :: MIT License
Classifier: Intended Audience :: End Users/Desktop
Classifier: Natural Language :: English
Classifier: Operating System :: OS Independent
Classifier: Programming Language :: Python :: 3.7
Classifier: Programming Language :: Python :: 3.8
Classifier: Programming Language :: Python :: 3.9
Classifier: Topic :: Games/Entertainment
Classifier: Topic :: Scientific/Engineering :: Artificial Intelligence
Classifier: Topic :: Sociology
Requires-Python: >=3.7
Requires-Dist: Click (==7.1.2)
Requires-Dist: google-api-python-client (==1.12.5)
Requires-Dist: nltk (==3.5)
Requires-Dist: tensorflow (==2.3.1)
Requires-Dist: youtube-transcript-api (==0.3.1)
